jsonx/__init__.py
jsonx/jsonx.py
jsonx_py-1.0.0.dist-info/LICENSE.md
jsonx_py-1.0.0.dist-info/METADATA
jsonx_py-1.0.0.dist-info/WHEEL
jsonx_py-1.0.0.dist-info/top_level.txt
jsonx_py-1.0.0.dist-info/RECORD
