Metadata-Version: 2.1
Name: jsonx-py
Version: 1.0.0
Summary: JSON flattening and expansion
Home-page: https://github.com/getformative/jsonx-py
Author: Formative
Author-email: hello@getformative.com
License: MIT
Platform: UNKNOWN
